op5.py
setup.py
op5lib.egg-info/PKG-INFO
op5lib.egg-info/SOURCES.txt
op5lib.egg-info/dependency_links.txt
op5lib.egg-info/requires.txt
op5lib.egg-info/top_level.txt