Metadata-Version: 1.0
Name: op5lib
Version: 1.0
Summary: A python library for OP5's REST API
Home-page: https://github.com/ozans/op5lib
Author: Ozan Safi
Author-email: ozansafi@gmail.com
License: UNKNOWN
Platform: UNKNOWN
